[
  {
    "id": "aws-ec2-t3-micro",
    "provider": "aws",
    "service": "ec2",
    "type": "compute",
    "instance_type": "t3.micro",
    "vcpu": 2,
    "ram_gb": 1,
    "monthly_rate": 7.59,
    "currency": "USD",
    "description": "AWS EC2 t3.micro general purpose instance"
  },
  {
    "id": "aws-ec2-t3-medium",
    "provider": "aws",
    "service": "ec2",
    "type": "compute",
    "instance_type": "t3.medium",
    "vcpu": 2,
    "ram_gb": 4,
    "monthly_rate": 30.37,
    "currency": "USD",
    "description": "AWS EC2 t3.medium general purpose instance"
  },
  {
    "id": "aws-ec2-m5-large",
    "provider": "aws",
    "service": "ec2",
    "type": "compute",
    "instance_type": "m5.large",
    "vcpu": 2,
    "ram_gb": 8,
    "monthly_rate": 70.08,
    "currency": "USD",
    "description": "AWS EC2 m5.large general purpose instance"
  },
  {
    "id": "aws-rds-mysql-t3-medium",
    "provider": "aws",
    "service": "rds",
    "type": "database",
    "instance_type": "db.t3.medium",
    "vcpu": 2,
    "ram_gb": 4,
    "monthly_rate": 51.10,
    "currency": "USD",
    "description": "AWS RDS MySQL db.t3.medium Single-AZ"
  },
  {
    "id": "aws-rds-mysql-m5-large-multiaz",
    "provider": "aws",
    "service": "rds",
    "type": "database",
    "instance_type": "db.m5.large",
    "vcpu": 2,
    "ram_gb": 8,
    "monthly_rate": 226.30,
    "currency": "USD",
    "description": "AWS RDS MySQL db.m5.large Multi-AZ"
  },
  {
    "id": "aws-ebs-gp3",
    "provider": "aws",
    "service": "ebs",
    "type": "storage",
    "instance_type": "gp3",
    "unit": "GB-month",
    "monthly_rate": 0.08,
    "currency": "USD",
    "description": "AWS EBS gp3 storage volume per GB"
  },
  {
    "id": "azure-vm-b2s",
    "provider": "azure",
    "service": "vm",
    "type": "compute",
    "instance_type": "Standard_B2s",
    "vcpu": 2,
    "ram_gb": 4,
    "monthly_rate": 30.37,
    "currency": "USD",
    "description": "Azure VM Standard_B2s general purpose"
  },
  {
    "id": "azure-vm-d2as-v5",
    "provider": "azure",
    "service": "vm",
    "type": "compute",
    "instance_type": "Standard_D2as_v5",
    "vcpu": 2,
    "ram_gb": 8,
    "monthly_rate": 70.08,
    "currency": "USD",
    "description": "Azure VM Standard_D2as_v5 general purpose"
  },
  {
    "id": "azure-sql-db-gp-gen5-2",
    "provider": "azure",
    "service": "sql",
    "type": "database",
    "instance_type": "GP_Gen5_2",
    "vcpu": 2,
    "ram_gb": 10.2,
    "monthly_rate": 225.00,
    "currency": "USD",
    "description": "Azure SQL Database General Purpose Gen5 2 vCores Serverless"
  },
  {
    "id": "azure-storage-lrs",
    "provider": "azure",
    "service": "storage",
    "type": "storage",
    "instance_type": "Premium_SSD",
    "unit": "GB-month",
    "monthly_rate": 0.12,
    "currency": "USD",
    "description": "Azure Premium SSD LRS Storage per GB"
  },
  {
    "id": "gcp-gce-e2-medium",
    "provider": "gcp",
    "service": "gce",
    "type": "compute",
    "instance_type": "e2-medium",
    "vcpu": 2,
    "ram_gb": 4,
    "monthly_rate": 24.38,
    "currency": "USD",
    "description": "GCP GCE e2-medium general purpose instance"
  },
  {
    "id": "gcp-gce-n2-standard-2",
    "provider": "gcp",
    "service": "gce",
    "type": "compute",
    "instance_type": "n2-standard-2",
    "vcpu": 2,
    "ram_gb": 8,
    "monthly_rate": 71.47,
    "currency": "USD",
    "description": "GCP GCE n2-standard-2 general purpose instance"
  },
  {
    "id": "gcp-cloudsql-mysql-custom-2-7680",
    "provider": "gcp",
    "service": "cloudsql",
    "type": "database",
    "instance_type": "db-custom-2-7680",
    "vcpu": 2,
    "ram_gb": 7.5,
    "monthly_rate": 105.85,
    "currency": "USD",
    "description": "GCP Cloud SQL MySQL db-custom-2-7680 Single-Zone"
  },
  {
    "id": "gcp-pd-ssd",
    "provider": "gcp",
    "service": "storage",
    "type": "storage",
    "instance_type": "pd-ssd",
    "unit": "GB-month",
    "monthly_rate": 0.17,
    "currency": "USD",
    "description": "GCP Persistent Disk SSD per GB"
  }
]
